squiggy/__init__.py
squiggy/alignment.py
squiggy/api.py
squiggy/cache.py
squiggy/constants.py
squiggy/io.py
squiggy/modifications.py
squiggy/motif.py
squiggy/normalization.py
squiggy/plot_factory.py
squiggy/plotting.py
squiggy/utils.py
squiggy/data/README.md
squiggy/data/yeast_trna.fa
squiggy/data/yeast_trna.fa.fai
squiggy/data/yeast_trna_mappings.bam
squiggy/data/yeast_trna_mappings.bam.bai
squiggy/data/yeast_trna_reads.pod5
squiggy/plot_strategies/__init__.py
squiggy/plot_strategies/aggregate.py
squiggy/plot_strategies/aggregate_comparison.py
squiggy/plot_strategies/base.py
squiggy/plot_strategies/delta.py
squiggy/plot_strategies/eventalign.py
squiggy/plot_strategies/overlay.py
squiggy/plot_strategies/signal_overlay_comparison.py
squiggy/plot_strategies/single_read.py
squiggy/plot_strategies/stacked.py
squiggy/rendering/__init__.py
squiggy/rendering/base_annotation_renderer.py
squiggy/rendering/modification_track_builder.py
squiggy/rendering/reference_track_renderer.py
squiggy/rendering/theme_manager.py
squiggy_positron-0.1.16.dist-info/licenses/LICENSE
squiggy_positron-0.1.16.dist-info/METADATA
squiggy_positron-0.1.16.dist-info/WHEEL
squiggy_positron-0.1.16.dist-info/top_level.txt
squiggy_positron-0.1.16.dist-info/RECORD
