Metadata-Version: 2.4
Name: squiggy-positron
Version: 0.1.16
Summary: Python backend for Squiggy Positron extension - Nanopore squiggle visualization. Not recommended for standalone use.
Author-email: Jay Hesselberth <jay.hesselberth@gmail.com>
License-Expression: MIT
Project-URL: Homepage, https://rnabioco.github.io/squiggy-positron/
Project-URL: Issues, https://github.com/rnabioco/squiggy-positron/issues
Project-URL: Repository, https://github.com/rnabioco/squiggy-positron
Keywords: nanopore,oxford-nanopore,pod5,squiggle,visualization,positron,ide-extension
Classifier: Development Status :: 3 - Alpha
Classifier: Intended Audience :: Science/Research
Classifier: Programming Language :: Python :: 3
Classifier: Programming Language :: Python :: 3.12
Classifier: Topic :: Scientific/Engineering :: Bio-Informatics
Requires-Python: >=3.12
License-File: LICENSE
Requires-Dist: bokeh>=3.1.1
Requires-Dist: numpy>=1.20.0
Requires-Dist: pod5>=0.3.0
Requires-Dist: pysam>=0.20.0
Provides-Extra: dev
Requires-Dist: pytest>=7.0; extra == "dev"
Requires-Dist: pytest-cov>=4.0; extra == "dev"
Requires-Dist: ruff>=0.1.0; extra == "dev"
Requires-Dist: mkdocs>=1.5.0; extra == "dev"
Requires-Dist: mkdocs-material>=9.0.0; extra == "dev"
Requires-Dist: jupyter>=1.0.0; extra == "dev"
Provides-Extra: export
Requires-Dist: selenium>=4.6; extra == "export"
Requires-Dist: pillow>=9.0; extra == "export"
Dynamic: license-file
